requests_text.py
requests_text-1.0.2.dist-info/METADATA
requests_text-1.0.2.dist-info/WHEEL
requests_text-1.0.2.dist-info/licenses/LICENSE
requests_text-1.0.2.dist-info/RECORD
