Metadata-Version: 2.4
Name: requests-text
Version: 1.0.2
Summary: File transport adapter for Requests
Project-URL: Homepage, https://github.com/huakim/python-requests-text
Author-email: huakim <fijik19@gmail.com>
License: Apache 2.0
License-File: LICENSE
Classifier: Development Status :: 3 - Alpha
Classifier: Environment :: Plugins
Classifier: Intended Audience :: Developers
Classifier: License :: OSI Approved :: Apache Software License
Classifier: Programming Language :: Python :: 3
Requires-Dist: requests>=1.0.0
